printlistpkg/__init__.py
printlistpkg/printlist/__init__.py
printlistpkg/printlist/taskkill.py
printlist_and_taskkill-0.25.24863.dist-info/LICENSE
printlist_and_taskkill-0.25.24863.dist-info/METADATA
printlist_and_taskkill-0.25.24863.dist-info/WHEEL
printlist_and_taskkill-0.25.24863.dist-info/top_level.txt
printlist_and_taskkill-0.25.24863.dist-info/RECORD
