Metadata-Version: 2.1
Name: printlist-and-taskkill
Version: 0.25.24863
Summary: A taskkill example package
Author: CJKim
Author-email: 
Classifier: Programming Language :: Python :: 3
Classifier: License :: OSI Approved :: MIT License
Classifier: Operating System :: OS Independent
License-File: LICENSE
